rtl/sign_extender.sv
/*
---------------------------------------------------------------------------------------------------
File: sign_ext.sv
SigmaCore Project: Sign Extender Unit
Author: Shahriar Rizvi
Performs: Sign extension of immediate values in RISC-V instructions

This module takes a 32-bit RISC-V instruction and an immediate type (defined in sigma_pkg),
extracts the appropriate immediate field, and sign-extends it to 32 bits.
---------------------------------------------------------------------------------------------------
*/



`timescale 1ns/1ps

module sign_extender (
    // Inputs
    input  logic [31:0] instruction_in, 
    input  logic [2:0]  imm_type_in,    // from sigma_pkg

    // Output
    output logic [31:0] imm_extended_out 
);

    import sigma_pkg::*;

    logic [31:0] imm_temp;

    always_comb begin
        imm_temp = 32'b0;

        case (imm_type_in)
            IMM_TYPE_I: begin
                // I-type immediate: instruction[31:20] (12 bits)
                // Sign bit is instruction[31]
                imm_temp = {{20{instruction_in[31]}}, instruction_in[31:20]};
            end

            IMM_TYPE_S: begin
                // S-type immediate: {instruction[31:25], instruction[11:7]} (12 bits)
                // Sign bit is instruction[31]
                imm_temp = {{20{instruction_in[31]}}, instruction_in[31:25], instruction_in[11:7]};
            end

            IMM_TYPE_B: begin
                // B-type immediate: {instruction[31](imm[12]), instruction[7](imm[11]), instruction[30:25](imm[10:5]), instruction[11:8](imm[4:1]), 1'b0 (imm[0])}
                // Sign bit for extension is instruction[31]. This forms a 13-bit value that is then sign-extended.
                imm_temp = {{19{instruction_in[31]}}, instruction_in[31], instruction_in[7], instruction_in[30:25], instruction_in[11:8], 1'b0};
            end

            IMM_TYPE_U: begin
                // U-type immediate: instruction[31:12] (20 bits)
                // Forms imm[31:12] by placing the 20-bit immediate in the upper bits and zeroing lower 12.
                imm_temp = {instruction_in[31:12], 12'b0};
            end

            IMM_TYPE_J: begin
                // J-type immediate: {instruction[31](imm[20]), instruction[19:12](imm[19:12]), instruction[20](imm[11]), instruction[30:21](imm[10:1]), 1'b0 (imm[0])}
                // Sign bit for extension is instruction[31]. This forms a 21-bit value that is then sign-extended.
                imm_temp = {{11{instruction_in[31]}}, instruction_in[31], instruction_in[19:12], instruction_in[20], instruction_in[30:21], 1'b0};
            end

            IMM_TYPE_NONE: begin
                imm_temp = 32'b0; // no immediate
            end

            default: begin
                imm_temp = 32'b0; 
            end
        endcase
    end

    assign imm_extended_out = imm_temp;

endmodule

test/sign_ext_tb.sv
/*
-----------------------------------------------------------------------------
File Name: sign_ext_tb.sv
SigmaCore Project: Sign Extender Testbench
Author: Shahriar Rizvi
Performs: Testbench for the Sign Extender module
-----------------------------------------------------------------------------
*/



`timescale 1ns/1ps

module sign_ext_tb;

    // Inputs
    reg  [31:0] instruction_tb;
    reg  [2:0]  imm_type_tb;

    // Output
    wire [31:0] imm_extended_out_tb;

    import sigma_pkg::*;

    sign_extender dut (
        .instruction_in     (instruction_tb),
        .imm_type_in        (imm_type_tb),
        .imm_extended_out   (imm_extended_out_tb)
    );

    task automatic apply_and_check (
        input [31:0] inst_val,
        input [2:0]  type_val,
        input [31:0] expected_ext_val,
        input string test_name
    );
        integer delay_time = 10; // ns

        begin
            #delay_time;
            instruction_tb = inst_val;
            imm_type_tb    = type_val;
            #delay_time;

            $display("[%0t ns] Test: %s", $time, test_name);
            $display("  Instruction: %h, Imm_Type: %b (%s)",
                     instruction_tb, imm_type_tb, imm_type_to_string(imm_type_tb));
            $display("  Extended Output: %h (Decimal: %0d)",
                     imm_extended_out_tb, $signed(imm_extended_out_tb));

            if (imm_extended_out_tb !== expected_ext_val) begin
                $error("  MISMATCH! Output: %h, Expected: %h",
                       imm_extended_out_tb, expected_ext_val);
            end
            $display("------------------------------------");
        end
    endtask

    function automatic string imm_type_to_string(input [2:0] type_code);
        case(type_code)
            IMM_TYPE_NONE: return "NONE";
            IMM_TYPE_I:    return "I-Type";
            IMM_TYPE_S:    return "S-Type";
            IMM_TYPE_B:    return "B-Type";
            IMM_TYPE_U:    return "U-Type";
            IMM_TYPE_J:    return "J-Type";
            default:       return $sformatf("UNKNOWN (%b)", type_code);
        endcase
    endfunction

    initial begin
        $dumpfile("sign_ext_waveforms.vcd");
        $dumpvars(0, sign_ext_tb);

        $display("Starting Sign Extender Testbench Simulation...");
        $display("============================================");

        // Test Case 1: IMM_TYPE_NONE
        apply_and_check(32'hDEADBEEF, IMM_TYPE_NONE, 32'h00000000, "IMM_TYPE_NONE");

        // Test Case 2: IMM_TYPE_I (Positive Immediate +5)
        apply_and_check(32'h00500093, IMM_TYPE_I, 32'h00000005, "I-Type Positive (+5)");

        // Test Case 3: IMM_TYPE_I (Negative Immediate -5)
        apply_and_check(32'hFFB00093, IMM_TYPE_I, 32'hFFFFFFF_B, "I-Type Negative (-5)");

        // Test Case 4: IMM_TYPE_S (Positive Immediate +12)
        apply_and_check(32'h00002623, IMM_TYPE_S, 32'h0000000C, "S-Type Positive (+12)");

        // Test Case 5: IMM_TYPE_S (Negative Immediate -16)
        apply_and_check(32'hFE002823, IMM_TYPE_S, 32'hFFFFFFF0, "S-Type Negative (-16)");

        // Test Case 6: IMM_TYPE_B (Positive Offset +20)
        // Instruction for beq x0,x0,+20 (target is PC+20, immediate is 20) is 0x00A00A63
        apply_and_check(32'h00A00A63, IMM_TYPE_B, 32'h00000014, "B-Type Positive Offset (+20)");

        // Test Case 7: IMM_TYPE_B (Negative Offset -20)
        // Instruction for beq x0,x0,-20 (target is PC-20, immediate is -20) is 0xFE000CE3
        apply_and_check(32'hFE0006E3, IMM_TYPE_B, 32'hFFFFFFEC, "B-Type Negative Offset (-20)");

        // Test Case 8: IMM_TYPE_U (Positive Value 0x12345)
        apply_and_check(32'h123450B7, IMM_TYPE_U, 32'h12345000, "U-Type Positive (0x12345 << 12)");

        // Test Case 9: IMM_TYPE_U (Value 0xFEDCB)
        apply_and_check(32'hFEDCB0B7, IMM_TYPE_U, 32'hFEDCB000, "U-Type Top Bits (0xFEDCB << 12)");

        // Test Case 10: IMM_TYPE_J (Positive Offset +1000)
        // Instruction for jal x0,+1000 (target is PC+1000, immediate is 1000) is 0x3E80006F
        apply_and_check(32'h3E80006F, IMM_TYPE_J, 32'h000003E8, "J-Type Positive Offset (+1000)");

        // Test Case 11: IMM_TYPE_J (Negative Offset -1000)
        // Instruction for jal x0,-1000 (target is PC-1000, immediate is -1000) is 0xC18FC06F
        apply_and_check(32'hC19FF06F, IMM_TYPE_J, 32'hFFFFFC18, "J-Type Negative Offset (-1000)");


        // Test Case 12: Default type (should be 0)
        apply_and_check(32'h12345678, 3'b111, 32'h00000000, "Unknown IMM_TYPE");


        $display("============================================");
        $display("Sign Extender Testbench Simulation Finished.");
        $finish;
    end

endmodule

RTL/Sign_Extender/sign_ext_waveforms.vcd
$date
	Wed May 28 14:44:39 2025
$end
$version
	Icarus Verilog
$end
$timescale
	1ps
$end
$scope module sign_ext_tb $end
$var wire 32 ! imm_extended_out_tb [31:0] $end
$var reg 3 " imm_type_tb [2:0] $end
$var reg 32 # instruction_tb [31:0] $end
$scope function imm_type_to_string $end
$upscope $end
$scope module dut $end
$var wire 32 $ imm_extended_out [31:0] $end
$var wire 3 % imm_type_in [2:0] $end
$var wire 32 & instruction_in [31:0] $end
$var reg 32 ' imm_temp [31:0] $end
$upscope $end
$scope task apply_and_check $end
$upscope $end
$upscope $end
$enddefinitions $end
$comment Show the parameter values. $end
$dumpall
$end
#0
$dumpvars
b0 '
bx &
bx %
b0 $
bx #
bx "
b0 !
$end
#10000
b0 "
b0 %
b11011110101011011011111011101111 #
b11011110101011011011111011101111 &
#30000
b101 !
b101 $
b101 '
b1 "
b1 %
b10100000000000010010011 #
b10100000000000010010011 &
#50000
b11111111111111111111111111111011 !
b11111111111111111111111111111011 $
b11111111111111111111111111111011 '
b11111111101100000000000010010011 #
b11111111101100000000000010010011 &
#70000
b1100 !
b1100 $
b1100 '
b10 "
b10 %
b10011000100011 #
b10011000100011 &
#90000
b11111111111111111111111111110000 !
b11111111111111111111111111110000 $
b11111111111111111111111111110000 '
b11111110000000000010100000100011 #
b11111110000000000010100000100011 &
#110000
b10100 !
b10100 $
b10100 '
b11 "
b11 %
b101000000000101001100011 #
b101000000000101001100011 &
#130000
b11111111111111111111111111101100 !
b11111111111111111111111111101100 $
b11111111111111111111111111101100 '
b11111110000000000000011011100011 #
b11111110000000000000011011100011 &
#150000
b10010001101000101000000000000 !
b10010001101000101000000000000 $
b10010001101000101000000000000 '
b100 "
b100 %
b10010001101000101000010110111 #
b10010001101000101000010110111 &
#170000
b11111110110111001011000000000000 !
b11111110110111001011000000000000 $
b11111110110111001011000000000000 '
b11111110110111001011000010110111 #
b11111110110111001011000010110111 &
#190000
b1111101000 !
b1111101000 $
b1111101000 '
b101 "
b101 %
b111110100000000000000001101111 #
b111110100000000000000001101111 &
#210000
b11111111111111111111110000011000 !
b11111111111111111111110000011000 $
b11111111111111111111110000011000 '
b11000001100111111111000001101111 #
b11000001100111111111000001101111 &
#230000
b0 !
b0 $
b0 '
b111 "
b111 %
b10010001101000101011001111000 #
b10010001101000101011001111000 &
