RTL/Memory/imem.sv
/*
------------------------------------------------------------------------
File Name: imem.sv
SigmaCore Project: Instruction Memory Unit (ROM)
Author: Shahriar Rizvi

Performs: Implements a 32x32 instruction memory for RISC-V CPU

------------------------------------------------------------------------
*/


`timescale 1ns/1ps

module instruction_memory(
    
    input logic clk, 
    input logic [31:0] read_addr_in,

    output logic [31:0] instruction_out

);

localparam MEM_SIZE_WORDS = 1024;
localparam ADDR_WIDTH = $clog2(MEM_SIZE_WORDS);

logic [31:0] memory [0:MEM_SIZE_WORDS-1];


initial begin

    $display("IMEM: Initializing instruction memory from program.hex...");

    try begin
        $readmemh("program.hex", memory);
    end catch (e) begin
        $error("IMEM: Failed to read 'program.hex'");
    end

end


always_ff @(posedge clk) begin
    instruction_out <= memory[read_addr_in[ADDR_WIDTH-1:2]]; 
    // read_addr_in[11:2] would be the 10-bit word index for a 4KB memory.
    // This assumes the lower two bits [1:0] are always "00".
end

endmodule

test/imem_tb.sv
// SigmaCore Project: Testbench for the Instruction Memory

`timescale 1ns/1ps

module instruction_memory_tb;

    // Inputs to the DUT
    logic        clk_tb;
    logic [31:0] read_addr_tb;

    // Output from the DUT
    wire [31:0] instruction_out_tb;

    // Instantiate the Instruction Memory (DUT)
    instruction_memory dut (
        .clk             (clk_tb),
        .read_addr_in    (read_addr_tb),
        .instruction_out (instruction_out_tb)
    );

    // Clock generation
    localparam CLOCK_PERIOD = 10; // ns
    always begin
        clk_tb = 1'b0; #(CLOCK_PERIOD/2);
        clk_tb = 1'b1; #(CLOCK_PERIOD/2);
    end

    // Test sequence
    initial begin
        $dumpfile("imem_waveforms.vcd");
        $dumpvars(0, instruction_memory_tb);

        $display("Starting Instruction Memory Testbench...");
        $display("========================================");

        // Initialize signals
        clk_tb       = 1'b0;
        read_addr_tb = 32'b0;

        // Waiting for 2 cycles for memory to initialize from file
        repeat(2) @(posedge clk_tb);

        // --- Test Case 1: Read from address 0x00 ---
        $display("[%0t ns] Test: Reading from address 0x00", $time);
        read_addr_tb = 32'h00000000;
        @(posedge clk_tb); // Address is latched. Data will appear on the next posedge.
        @(posedge clk_tb); // Data is now valid on instruction_out_tb

        $display("  Read from addr %h. Got instruction: %h. Expected: 12345678", read_addr_tb, instruction_out_tb);
        if (instruction_out_tb !== 32'h12345678) $error("FAIL: Address 0x00 mismatch.");
        else $display("PASS: Address 0x00 correct.");
        $display("------------------------------------");

        // --- Test Case 2: Read from address 0x08 ---
        $display("[%0t ns] Test: Reading from address 0x08", $time);
        read_addr_tb = 32'h00000008;
        @(posedge clk_tb);
        @(posedge clk_tb);

        $display("  Read from addr %h. Got instruction: %h. Expected: DEADBEEF", read_addr_tb, instruction_out_tb);
        if (instruction_out_tb !== 32'hDEADBEEF) $error("FAIL: Address 0x08 mismatch.");
        else $display("PASS: Address 0x08 correct.");
        $display("------------------------------------");

        // --- Test Case 3: Read from address 0x10 ---
        $display("[%0t ns] Test: Reading from address 0x10", $time);
        read_addr_tb = 32'h00000010;
        @(posedge clk_tb);
        @(posedge clk_tb);

        $display("  Read from addr %h. Got instruction: %h. Expected: FFFFFFFF", read_addr_tb, instruction_out_tb);
        if (instruction_out_tb !== 32'hFFFFFFFF) $error("FAIL: Address 0x10 mismatch.");
        else $display("PASS: Address 0x10 correct.");
        $display("------------------------------------");
        
        // --- Test Case 4: Read from consecutive addresses ---
        $display("[%0t ns] Test: Reading consecutively from 0x04 then 0x0C", $time);
        read_addr_tb = 32'h00000004;
        @(posedge clk_tb); // Latch address 0x04
        // On this next edge, output for address 0x10 (from prev test) is still valid.
        @(posedge clk_tb); // Now, output for address 0x04 is valid.
        $display("  Read from addr 0x04. Got instruction: %h. Expected: ABCDEF01", instruction_out_tb);
        if (instruction_out_tb !== 32'hABCDEF01) $error("FAIL: Address 0x04 mismatch.");
        
        // Immediately change address to 0x0C
        read_addr_tb = 32'h0000000C;
        @(posedge clk_tb); // Latch address 0x0C
        // On this next edge, output for address 0x04 is still valid.
        @(posedge clk_tb); // Now, output for address 0x0C is valid.
        $display("  Read from addr 0x0C. Got instruction: %h. Expected: 00000000", instruction_out_tb);
        if (instruction_out_tb !== 32'h00000000) $error("FAIL: Address 0x0C mismatch.");
        else $display("PASS: Consecutive reads correct.");
        $display("------------------------------------");


        $display("========================================");
        $display("Instruction Memory Testbench Finished.");
        $finish;
    end

endmodule

RTL/Memory/imem_waveforms.vcd
$date
	Sat Jun 21 16:33:57 2025
$end
$version
	Icarus Verilog
$end
$timescale
	1ps
$end
$scope module instruction_memory_tb $end
$var wire 32 ! instruction_out_tb [31:0] $end
$var parameter 32 " CLOCK_PERIOD $end
$var reg 1 # clk_tb $end
$var reg 32 $ read_addr_tb [31:0] $end
$scope module dut $end
$var wire 1 # clk $end
$var wire 32 % read_addr_in [31:0] $end
$var parameter 32 & ADDR_WIDTH $end
$var parameter 32 ' MEM_SIZE_WORDS $end
$var reg 32 ( instruction_out [31:0] $end
$upscope $end
$upscope $end
$enddefinitions $end
$comment Show the parameter values. $end
$dumpall
b10000000000 '
b1010 &
b1010 "
$end
#0
$dumpvars
bx (
b0 %
b0 $
0#
bx !
$end
#5000
b10010001101000101011001111000 !
b10010001101000101011001111000 (
1#
#10000
0#
#15000
1#
#20000
0#
#25000
1#
#30000
0#
#35000
b1000 $
b1000 %
1#
#40000
0#
#45000
b11011110101011011011111011101111 !
b11011110101011011011111011101111 (
1#
#50000
0#
#55000
b10000 $
b10000 %
1#
#60000
0#
#65000
b11111111111111111111111111111111 !
b11111111111111111111111111111111 (
1#
#70000
0#
#75000
b100 $
b100 %
1#
#80000
0#
#85000
b10101011110011011110111100000001 !
b10101011110011011110111100000001 (
1#
#90000
0#
#95000
b1100 $
b1100 %
1#
#100000
0#
#105000
b0 !
b0 (
1#
