RTL/ALU/alu.sv
// Arithmetic Logic Unit (ALU) module

`timescale 1ns/1ps

module alu(
    // Inputs
    input logic [31:0] operand1,
    input logic [31:0] operand2,
    input logic [3:0] alu_op, 

    // Outputs
    output logic [31:0] result,
    output logic zero_flag,
    output logic negative_flag,
    output logic overflow_flag,
    output logic carry_flag
);

import sigma_pkg::*; // Importing the package for better readability

// ALU Operation
always_comb begin
    case(alu_op)
        ALU_ADD: {carry_flag, result} = operand1 + operand2; // ADD
        ALU_SUB: {carry_flag, result} = operand1 + (~operand2 + 1'b1); // SUB using 2's complement
        ALU_AND: result = operand1 & operand2; // AND
        ALU_OR: result = operand1 | operand2; // OR
        ALU_XOR: result = operand1 ^ operand2; // XOR
        ALU_SLL: result = operand1 << operand2; // SLL
        ALU_SRL: result = operand1 >> operand2; // SRL
        ALU_SRA: result = $signed(operand1) >>> operand2; // SRA
        default: result = 32'b0; // Default case
    endcase
end

// Flags
assign zero_flag = (result == 32'b0);
assign negative_flag = result[31];


endmodule

RTL/ALU/alu_tb.sv
/*
---------------------------------------------------------------
File: alu_tb.sv
SigmaCore Project: ALU Testbench
Author: Shahriar Rizvi
Performs: Testbench for the ALU module
---------------------------------------------------------------
*/

`timescale 1ns/1ps

module alu_tb;

    // Inputs
    reg [31:0] operand1_tb;
    reg [31:0] operand2_tb;
    reg [3:0] alu_op_tb;

    // Outputs
    wire [31:0] result_tb;
    wire zero_flag_tb;
    wire negative_flag_tb;
    wire overflow_flag_tb;
    wire carry_flag_tb;

    import sigma_pkg::*;

    // Instantiate the ALU module
    alu alu_instance(
        .operand1(operand1_tb),
        .operand2(operand2_tb),
        .alu_op(alu_op_tb),
        .result(result_tb),
        .zero_flag(zero_flag_tb),
        .negative_flag(negative_flag_tb),
        .overflow_flag(overflow_flag_tb),
        .carry_flag(carry_flag_tb)
    );



    task automatic apply_and_check; // A task to apply the Test Cases
        input [31:0] op1_in, op2_in;
        input [3:0]  op_code_in;
        input [31:0] expected_result;
        input        expected_zero, expected_neg, expected_ovf, expected_carry;
        input string test_name;
        integer      delay_time = 10; // delay in ns

        begin
            #delay_time;
            operand1_tb = op1_in;
            operand2_tb = op2_in;
            alu_op_tb   = op_code_in;
            #delay_time; 

            $display("[%0t ns] Test: %s", $time, test_name);
            $display("  Inputs: op1=%h, op2=%h, alu_op=%b (%s)",
                        operand1_tb, operand2_tb, alu_op_tb, op_code_to_string(alu_op_tb));
            $display("  Outputs: Result=%h, Z=%b, N=%b, O=%b, C=%b",
                        result_tb, zero_flag_tb, negative_flag_tb, overflow_flag_tb, carry_flag_tb);

            if (result_tb !== expected_result) begin
                $error("  MISMATCH! Result: %h, Expected: %h", result_tb, expected_result);
            end
            if (zero_flag_tb !== expected_zero) begin
                $error("  MISMATCH! Zero Flag: %b, Expected: %b", zero_flag_tb, expected_zero);
            end
            if (negative_flag_tb !== expected_neg) begin
                $error("  MISMATCH! Negative Flag: %b, Expected: %b", negative_flag_tb, expected_neg);
            end
            if (overflow_flag_tb !== expected_ovf) begin
                $error("  MISMATCH! Overflow Flag: %b, Expected: %b", overflow_flag_tb, expected_ovf);
            end
            if (alu_op_tb == ALU_ADD || alu_op_tb == ALU_SUB) begin // Carry is most relevant for ADD/SUB
                if (carry_flag_tb !== expected_carry) begin
                    $error("  MISMATCH! Carry Flag: %b, Expected: %b", carry_flag_tb, expected_carry);
                end
            end
        end
    endtask

    // Function to convert ALU op code to string for display
    function automatic string op_code_to_string(input [3:0] op_code);
        case(op_code)
            ALU_ADD: return "ADD";
            ALU_SUB: return "SUB";
            ALU_AND: return "AND";
            ALU_OR:  return "OR";
            ALU_XOR: return "XOR";
            ALU_SLL: return "SLL";
            ALU_SRL: return "SRL";
            ALU_SRA: return "SRA";
            
            default: return $sformatf("OP:%b", op_code);
        endcase
    endfunction




    // Test Cases
    initial begin
        $dumpfile("alu_waveforms.vcd");
        $dumpvars(0, alu_tb);

        // --- Test Cases ---
        // apply_and_check(op1, op2, alu_op, exp_res, exp_Z, exp_N, exp_O, exp_C, "Test Name");

        // Test 1: ADD (Simple)
        apply_and_check(32'h00000001, 32'h00000002, ALU_ADD, 32'h00000003, 1'b0, 1'b0, 1'b0, 1'b0, "ADD (1 + 2)");
        // Test 2: SUB (Simple)
        apply_and_check(32'h00000005, 32'h00000002, ALU_SUB, 32'h00000003, 1'b0, 1'b0, 1'b0, 1'b1, "SUB (5 - 2)"); // Carry=1 (no borrow)
        // Test 3: AND
        apply_and_check(32'h0000000F, 32'h0000000A, ALU_AND, 32'h0000000A, 1'b0, 1'b0, 1'b0, 1'b0, "AND (0xF & 0xA)");
        // Test 4: OR
        apply_and_check(32'h0000000F, 32'h0000000A, ALU_OR,  32'h0000000F, 1'b0, 1'b0, 1'b0, 1'b0, "OR (0xF | 0xA)");
        // Test 5: XOR
        apply_and_check(32'h0000000F, 32'h0000000A, ALU_XOR, 32'h00000005, 1'b0, 1'b0, 1'b0, 1'b0, "XOR (0xF ^ 0xA)");
        // Test 6: SLL (Shift Logical Left)
        apply_and_check(32'h0000000F, 32'd2,        ALU_SLL, 32'h0000003C, 1'b0, 1'b0, 1'b0, 1'b0, "SLL (0xF << 2)");
        // Test 7: SRL (Shift Logical Right)
        apply_and_check(32'h0000000F, 32'd2,        ALU_SRL, 32'h00000003, 1'b0, 1'b0, 1'b0, 1'b0, "SRL (0xF >> 2)");
        // Test 8: SRA (Shift Arithmetic Right, positive number)
        apply_and_check(32'h000000F0, 32'd2,        ALU_SRA, 32'h0000003C, 1'b0, 1'b0, 1'b0, 1'b0, "SRA (0xF0 >>> 2)");
        // Test 9: SRA (Shift Arithmetic Right, negative number)
        apply_and_check(32'hFFFFFFF0, 32'd2,        ALU_SRA, 32'hFFFFFFFC, 1'b0, 1'b1, 1'b0, 1'b0, "SRA (0xFFFFFFF0 >>> 2)");
        // Test 10: ADD (Zero flag)
        apply_and_check(32'hFFFFFFFF, 32'h00000001, ALU_ADD, 32'h00000000, 1'b1, 1'b0, 1'b0, 1'b1, "ADD (-1 + 1) -> Zero");
        // Test 11: ADD (Overflow: pos + pos = neg)
        apply_and_check(32'h7FFFFFFF, 32'h00000001, ALU_ADD, 32'h80000000, 1'b0, 1'b1, 1'b1, 1'b0, "ADD (MaxPos + 1) -> Overflow");
        // Test 12: ADD (Overflow: neg + neg = pos)
        apply_and_check(32'h80000000, 32'h80000000, ALU_ADD, 32'h00000000, 1'b1, 1'b0, 1'b1, 1'b1, "ADD (MinNeg + MinNeg) -> Overflow");
        // Test 13: SUB (Negative flag)
        apply_and_check(32'h00000002, 32'h00000005, ALU_SUB, 32'hFFFFFFFD, 1'b0, 1'b1, 1'b0, 1'b0, "SUB (2 - 5) -> Negative"); // Carry=0 (borrow)
        // Test 14: SUB (Overflow: pos - neg = neg_res_overflow)
        apply_and_check(32'h70000000, 32'h90000000, ALU_SUB, 32'hE0000000, 1'b0, 1'b1, 1'b1, 1'b0, "SUB (LargePos - LargeNeg) -> Overflow");
        // Test 15: SUB (Overflow: neg - pos = pos_res_overflow)
        apply_and_check(32'h90000000, 32'h70000000, ALU_SUB, 32'h20000000, 1'b0, 1'b0, 1'b1, 1'b1, "SUB (LargeNeg - LargePos) -> Overflow");
        // Test 16: SLL (Shift by 0)
        apply_and_check(32'hABCDEF12, 32'd0,        ALU_SLL, 32'hABCDEF12, 1'b0, 1'b1, 1'b0, 1'b0, "SLL (val << 0)");
        // Test 17: SLL (Shift by 31)
        apply_and_check(32'h00000001, 32'd31,       ALU_SLL, 32'h80000000, 1'b0, 1'b1, 1'b0, 1'b0, "SLL (1 << 31)");
        // Test 18: SLL (Shift amount > 31, should use operand2[4:0])
        apply_and_check(32'h00000001, 32'd34,       ALU_SLL, 32'h00000004, 1'b0, 1'b0, 1'b0, 1'b0, "SLL (1 << 34), effective (1 << 2)");
        // Test 19: Default ALU op (if not defined in package, or an unused code)
        // Assuming 4'b1111 is not a defined ALU_OP in sigma_pkg.sv
        apply_and_check(32'd10, 32'd5, 4'b1111, 32'hxxxxxxxx, 1'b0, 1'b1, 1'b0, 1'b0, "Default/Unknown ALU Op");


        $display("ALU Testbench Simulation Finished.");
        $finish;

    end

endmodule

RTL/ALU/alu_waveforms.vcd
$date
	Wed May 28 01:36:59 2025
$end
$version
	Icarus Verilog
$end
$timescale
	1ps
$end
$scope module alu_tb $end
$var wire 1 ! zero_flag_tb $end
$var wire 32 " result_tb [31:0] $end
$var wire 1 # overflow_flag_tb $end
$var wire 1 $ negative_flag_tb $end
$var wire 1 % carry_flag_tb $end
$var reg 4 & alu_op_tb [3:0] $end
$var reg 32 ' operand1_tb [31:0] $end
$var reg 32 ( operand2_tb [31:0] $end
$scope function op_code_to_string $end
$upscope $end
$scope module alu_instance $end
$var wire 4 ) alu_op [3:0] $end
$var wire 32 * operand1 [31:0] $end
$var wire 32 + operand2 [31:0] $end
$var wire 1 ! zero_flag $end
$var wire 1 $ negative_flag $end
$var reg 1 % carry_flag $end
$var reg 1 # overflow_flag $end
$var reg 32 , result [31:0] $end
$upscope $end
$scope task apply_and_check $end
$upscope $end
$upscope $end
$enddefinitions $end
$comment Show the parameter values. $end
$dumpall
$end
#0
$dumpvars
bx ,
bx +
bx *
bx )
bx (
bx '
bx &
0%
x$
0#
bx "
x!
$end
#10000
0$
0!
b11 "
b11 ,
b0 &
b0 )
b10 (
b10 +
b1 '
b1 *
#30000
b1 &
b1 )
b101 '
b101 *
#50000
b1010 "
b1010 ,
b10 &
b10 )
b1010 (
b1010 +
b1111 '
b1111 *
#70000
b1111 "
b1111 ,
b11 &
b11 )
#90000
b101 "
b101 ,
b100 &
b100 )
#110000
b111100 "
b111100 ,
b101 &
b101 )
b10 (
b10 +
#130000
b11 "
b11 ,
b110 &
b110 )
#150000
b111100 "
b111100 ,
b111 &
b111 )
b11110000 '
b11110000 *
#170000
1$
b11111111111111111111111111111100 "
b11111111111111111111111111111100 ,
b11111111111111111111111111110000 '
b11111111111111111111111111110000 *
#190000
0$
1%
1!
b0 "
b0 ,
b0 &
b0 )
b1 (
b1 +
b11111111111111111111111111111111 '
b11111111111111111111111111111111 *
#210000
1$
1#
0!
b10000000000000000000000000000000 "
b10000000000000000000000000000000 ,
0%
b1111111111111111111111111111111 '
b1111111111111111111111111111111 *
#230000
0$
1%
1!
b0 "
b0 ,
1#
b10000000000000000000000000000000 (
b10000000000000000000000000000000 +
b10000000000000000000000000000000 '
b10000000000000000000000000000000 *
#250000
1$
0!
b11111111111111111111111111111101 "
b11111111111111111111111111111101 ,
0#
1%
b1 &
b1 )
b101 (
b101 +
b10 '
b10 *
#270000
1#
b11100000000000000000000000000000 "
b11100000000000000000000000000000 ,
1%
b10010000000000000000000000000000 (
b10010000000000000000000000000000 +
b1110000000000000000000000000000 '
b1110000000000000000000000000000 *
#290000
0$
b100000000000000000000000000000 "
b100000000000000000000000000000 ,
1#
0%
b1110000000000000000000000000000 (
b1110000000000000000000000000000 +
b10010000000000000000000000000000 '
b10010000000000000000000000000000 *
#310000
1$
b10101011110011011110111100010010 "
b10101011110011011110111100010010 ,
0#
b101 &
b101 )
b0 (
b0 +
b10101011110011011110111100010010 '
b10101011110011011110111100010010 *
#330000
b10000000000000000000000000000000 "
b10000000000000000000000000000000 ,
b11111 (
b11111 +
b1 '
b1 *
#350000
0$
b100 "
b100 ,
b100010 (
b100010 +
#370000
x$
x!
bx "
bx ,
b1111 &
b1111 )
b101 (
b101 +
b1010 '
b1010 *
